filterflow/__init__.py
filterflow/flow.py
filterflow-0.1.2.dist-info/LICENSE
filterflow-0.1.2.dist-info/WHEEL
filterflow-0.1.2.dist-info/METADATA
filterflow-0.1.2.dist-info/RECORD
