Metadata-Version: 2.1
Name: filterflow
Version: 0.1.2
Summary: A library to create data flow charts.
Home-page: https://github.com/LeviWadd/filterflow
Author: Levi Waddingham
Requires-Python: >=3.7,<4.0
Classifier: Programming Language :: Python :: 3
Classifier: Programming Language :: Python :: 3.7
Classifier: Programming Language :: Python :: 3.8
Classifier: Programming Language :: Python :: 3.9
Requires-Dist: plotly (>=4.14.3,<5.0.0)
Project-URL: Repository, https://github.com/LeviWadd/filterflow
